README
setup.py
django_template_fragments.egg-info/PKG-INFO
django_template_fragments.egg-info/SOURCES.txt
django_template_fragments.egg-info/dependency_links.txt
django_template_fragments.egg-info/top_level.txt
fragments/__init__.py
fragments/dirty.py
fragments/urls.py
fragments/views.py
fragments/templatetags/__init__.py
fragments/templatetags/fragments.py