Metadata-Version: 1.0
Name: django-template-fragments
Version: 0.1.2
Summary: helper for templates used in javascript client framework: allow to store small django templates in a dir and generate a javascript object that contains them all as strings
Home-page: https://github.com/Psycojoker/django-template-fragments
Author: Laurent Peuch
Author-email: cortex@worlddomination.be
License: MIT
Platform: UNKNOWN
